<?xml version="1.0" encoding="ISO-8859-1"?>

<TRIAL ID="38" SPEAKER="823" AGE="30" EXT="2.88" AGR="3.44" CON="4.00" NEU="4.63" OPE="3.10" ASSERTIVENESS="2.80" ACTIVITY="3.00" ALTRUISM="3.25" COMPLIANCE="4.33" ORDER="3.00" SELFDISCIPLINE="4.00" ANSIETY="4.50" DEPRESSION="5.00" AESTHETICS="3.33" IDEAS="3.20">

  <CONTEXT ID="1">
    <ATTRIBUTE-SET TARGET="a" STRING="foto de um rapaz de pele parda, olhos puxados, nariz largo, lábios e sobrancelhas grossos e cabelos escuros e bem curtos. diferente dos outros nas fotos, não sorri. parece estar entediado ou chateado.">
      <ATTRIBUTE NAME="gender" VALUE="male" />
      <ATTRIBUTE NAME="smile" VALUE="no" />
      <ATTRIBUTE NAME="isyoung" VALUE="yes" />
      <ATTRIBUTE NAME="hair.colour" VALUE="dark" />
      <ATTRIBUTE NAME="hair.length" VALUE="short" />
      <ATTRIBUTE NAME="emotion" VALUE="negative" />
      <ATTRIBUTE NAME="eyebrows" VALUE="other" />
      <ATTRIBUTE NAME="skin" VALUE="dark" />
      <ATTRIBUTE NAME="nose" VALUE="other" />
      <ATTRIBUTE NAME="lips" VALUE="other" />
      <ATTRIBUTE NAME="narrow.eyed" VALUE="yes" />
    </ATTRIBUTE-SET>
  </CONTEXT>

  <CONTEXT ID="2">
    <ATTRIBUTE-SET TARGET="d" STRING="foto de uma moça clara, cabelos longos, loiros e presos (com alguns fios soltos), que parece ter olhos claros também. possui uma leve olheira e uma mancha no queixo. pelo seu semblante, parece estar entediada ou chateada.">
      <ATTRIBUTE NAME="gender" VALUE="female" />
      <ATTRIBUTE NAME="isyoung" VALUE="yes" />
      <ATTRIBUTE NAME="hair.colour" VALUE="blonde" />
      <ATTRIBUTE NAME="hair.length" VALUE="long" />
      <ATTRIBUTE NAME="emotion" VALUE="negative" />
      <ATTRIBUTE NAME="eye.colour" VALUE="light" />
      <ATTRIBUTE NAME="ponytail" VALUE="yes" />
      <ATTRIBUTE NAME="skin" VALUE="fair" />
      <ATTRIBUTE NAME="face" VALUE="other" />
      <ATTRIBUTE NAME="eyes" VALUE="other" />
      <ATTRIBUTE NAME="hair" VALUE="other" />
    </ATTRIBUTE-SET>
  </CONTEXT>

  <CONTEXT ID="3">
    <ATTRIBUTE-SET TARGET="f" STRING="foto de uma moça de pele parda, olhos puxados, cabelos negros, lisos e curtos, meio presos e usando um brinco de argola. algumas marcas e manchas na pele do rosto. parece estar bem triste ou chateada.">
      <ATTRIBUTE NAME="gender" VALUE="female" />
      <ATTRIBUTE NAME="isyoung" VALUE="yes" />
      <ATTRIBUTE NAME="hair.colour" VALUE="dark" />
      <ATTRIBUTE NAME="hair.length" VALUE="short" />
      <ATTRIBUTE NAME="emotion" VALUE="negative" />
      <ATTRIBUTE NAME="skin" VALUE="dark" />
      <ATTRIBUTE NAME="hair.style" VALUE="straight" />
      <ATTRIBUTE NAME="spots" VALUE="yes" />
      <ATTRIBUTE NAME="hair" VALUE="other" />
      <ATTRIBUTE NAME="narrow.eyed" VALUE="yes" />
      <ATTRIBUTE NAME="earring" VALUE="yes" />
    </ATTRIBUTE-SET>
  </CONTEXT>

  <CONTEXT ID="4">
    <ATTRIBUTE-SET TARGET="c" STRING="foto de um rapaz branco , de rosto fino , de olhos escuros , de cabelos loiros , não muito curtos e bagunçados , nariz fino. aparenta ser magro. está parecendo que muito bravo, irritado ou chateado na foto.">
      <ATTRIBUTE NAME="gender" VALUE="male" />
      <ATTRIBUTE NAME="race" VALUE="caucasian" />
      <ATTRIBUTE NAME="isyoung" VALUE="yes" />
      <ATTRIBUTE NAME="hair.colour" VALUE="blonde" />
      <ATTRIBUTE NAME="hair.length" VALUE="long" />
      <ATTRIBUTE NAME="emotion" VALUE="negative" />
      <ATTRIBUTE NAME="eye.colour" VALUE="light" />
      <ATTRIBUTE NAME="nose" VALUE="other" />
      <ATTRIBUTE NAME="face" VALUE="other" />
      <ATTRIBUTE NAME="shape" VALUE="other" />
      <ATTRIBUTE NAME="unkempt" VALUE="yes" />
    </ATTRIBUTE-SET>
  </CONTEXT>

  <CONTEXT ID="5">
    <ATTRIBUTE-SET TARGET="b" STRING="rapaz claro, cabelos loiros, curtos e bagunçados, parece ter olhos claros. nariz não é largo e nem fino. sobrancelha grossa. algumas pintas no rosto e pescoço. está sorrindo, porém mostra uma certa timidez.">
      <ATTRIBUTE NAME="gender" VALUE="male" />
      <ATTRIBUTE NAME="smile" VALUE="yes" />
      <ATTRIBUTE NAME="isyoung" VALUE="yes" />
      <ATTRIBUTE NAME="hair.colour" VALUE="blonde" />
      <ATTRIBUTE NAME="hair.length" VALUE="short" />
      <ATTRIBUTE NAME="eye.colour" VALUE="light" />
      <ATTRIBUTE NAME="eyebrows" VALUE="other" />
      <ATTRIBUTE NAME="skin" VALUE="fair" />
      <ATTRIBUTE NAME="nose" VALUE="other" />
      <ATTRIBUTE NAME="spots" VALUE="yes" />
      <ATTRIBUTE NAME="unkempt" VALUE="yes" />
    </ATTRIBUTE-SET>
  </CONTEXT>

  <CONTEXT ID="6">
    <ATTRIBUTE-SET TARGET="e" STRING="rapaz sorridente de descendência oriental">
      <ATTRIBUTE NAME="gender" VALUE="male" />
      <ATTRIBUTE NAME="race" VALUE="asian" />
      <ATTRIBUTE NAME="smile" VALUE="yes" />
      <ATTRIBUTE NAME="isyoung" VALUE="yes" />
    </ATTRIBUTE-SET>
  </CONTEXT>

  <CONTEXT ID="7">
    <ATTRIBUTE-SET TARGET="e" STRING="moça sorridente">
      <ATTRIBUTE NAME="gender" VALUE="female" />
      <ATTRIBUTE NAME="smile" VALUE="yes" />
      <ATTRIBUTE NAME="isyoung" VALUE="yes" />
    </ATTRIBUTE-SET>
  </CONTEXT>

  <CONTEXT ID="8">
    <ATTRIBUTE-SET TARGET="b" STRING="moça sorridente de descendência oriental">
      <ATTRIBUTE NAME="gender" VALUE="female" />
      <ATTRIBUTE NAME="race" VALUE="asian" />
      <ATTRIBUTE NAME="smile" VALUE="yes" />
      <ATTRIBUTE NAME="isyoung" VALUE="yes" />
    </ATTRIBUTE-SET>
  </CONTEXT>

  <CONTEXT ID="9">
    <ATTRIBUTE-SET TARGET="c" STRING="moça séria negra">
      <ATTRIBUTE NAME="gender" VALUE="female" />
      <ATTRIBUTE NAME="race" VALUE="black" />
      <ATTRIBUTE NAME="smile" VALUE="no" />
      <ATTRIBUTE NAME="isyoung" VALUE="yes" />
    </ATTRIBUTE-SET>
  </CONTEXT>

  <CONTEXT ID="10">
    <ATTRIBUTE-SET TARGET="f" STRING="homem">
      <ATTRIBUTE NAME="gender" VALUE="male" />
    </ATTRIBUTE-SET>
  </CONTEXT>

  <CONTEXT ID="11">
    <ATTRIBUTE-SET TARGET="d" STRING="homem negro">
      <ATTRIBUTE NAME="gender" VALUE="male" />
      <ATTRIBUTE NAME="race" VALUE="black" />
    </ATTRIBUTE-SET>
  </CONTEXT>

  <CONTEXT ID="12">
    <ATTRIBUTE-SET TARGET="a" STRING="moça séria loira">
      <ATTRIBUTE NAME="gender" VALUE="female" />
      <ATTRIBUTE NAME="smile" VALUE="no" />
      <ATTRIBUTE NAME="isyoung" VALUE="yes" />
      <ATTRIBUTE NAME="hair.colour" VALUE="blonde" />
    </ATTRIBUTE-SET>
  </CONTEXT>

</TRIAL>
